funtask/__init__.py
funtask/__main__.py
funtask/models/__init__.py
funtask/models/base.py
funtask/models/task_model.py
funtask/task/__init__.py
funtask/task/manager.py
funtask/task/submit.py
funtask/web/app.py
ffuntask-0.1.4.dist-info/METADATA
ffuntask-0.1.4.dist-info/WHEEL
ffuntask-0.1.4.dist-info/top_level.txt
ffuntask-0.1.4.dist-info/RECORD
